ncloud_vpc/__init__.py
ncloud_vpc/api_client.py
ncloud_vpc/configuration.py
ncloud_vpc/rest.py
ncloud_vpc/api/__init__.py
ncloud_vpc/api/v2_api.py
ncloud_vpc/model/__init__.py
ncloud_vpc/model/accept_or_reject_vpc_peering_request.py
ncloud_vpc/model/accept_or_reject_vpc_peering_response.py
ncloud_vpc/model/add_network_acl_inbound_rule_request.py
ncloud_vpc/model/add_network_acl_inbound_rule_response.py
ncloud_vpc/model/add_network_acl_outbound_rule_request.py
ncloud_vpc/model/add_network_acl_outbound_rule_response.py
ncloud_vpc/model/add_network_acl_rule_parameter.py
ncloud_vpc/model/add_route_request.py
ncloud_vpc/model/add_route_response.py
ncloud_vpc/model/add_route_table_subnet_request.py
ncloud_vpc/model/add_route_table_subnet_response.py
ncloud_vpc/model/common_code.py
ncloud_vpc/model/create_nat_gateway_instance_request.py
ncloud_vpc/model/create_nat_gateway_instance_response.py
ncloud_vpc/model/create_network_acl_request.py
ncloud_vpc/model/create_network_acl_response.py
ncloud_vpc/model/create_route_table_request.py
ncloud_vpc/model/create_route_table_response.py
ncloud_vpc/model/create_subnet_request.py
ncloud_vpc/model/create_subnet_response.py
ncloud_vpc/model/create_vpc_peering_instance_request.py
ncloud_vpc/model/create_vpc_peering_instance_response.py
ncloud_vpc/model/create_vpc_request.py
ncloud_vpc/model/create_vpc_response.py
ncloud_vpc/model/delete_nat_gateway_instance_request.py
ncloud_vpc/model/delete_nat_gateway_instance_response.py
ncloud_vpc/model/delete_network_acl_request.py
ncloud_vpc/model/delete_network_acl_response.py
ncloud_vpc/model/delete_route_table_request.py
ncloud_vpc/model/delete_route_table_response.py
ncloud_vpc/model/delete_subnet_request.py
ncloud_vpc/model/delete_subnet_response.py
ncloud_vpc/model/delete_vpc_peering_instance_request.py
ncloud_vpc/model/delete_vpc_peering_instance_response.py
ncloud_vpc/model/delete_vpc_request.py
ncloud_vpc/model/delete_vpc_response.py
ncloud_vpc-1.0.1.dist-info/LICENSE
ncloud_vpc-1.0.1.dist-info/METADATA
ncloud_vpc-1.0.1.dist-info/WHEEL
ncloud_vpc-1.0.1.dist-info/top_level.txt
ncloud_vpc-1.0.1.dist-info/RECORD
