Metadata-Version: 1.0
Name: ncloud-vpc
Version: 1.0.1
Summary: vpc
Home-page: UNKNOWN
Author: UNKNOWN
Author-email: UNKNOWN
License: UNKNOWN
Keywords: vpc
Platform: UNKNOWN
